{
  "cli": {
    "version": ">= 5.9.0"
  },
  "build": {
    "development": {
      "developmentClient": true,
      "distribution": "internal",
      "android": {
        "gradleCommand": ":app:assembleDebug"
      },
      "ios": {
        "buildConfiguration": "Debug"
      },
      "env": {
        "EXPO_PUBLIC_API_URL": "https://splendid-bravery-production.up.railway.app"
      }
    },
    "preview": {
      "distribution": "internal",
      "android": {
        "buildType": "apk",
        "gradleCommand": ":app:assembleRelease"
      },
      "ios": {
        "buildConfiguration": "Release"
      },
      "env": {
        "EXPO_PUBLIC_API_URL": "https://splendid-bravery-production.up.railway.app"
      }
    },
    "production": {
      "android": {
        "buildType": "apk",
        "gradleCommand": ":app:assembleRelease"
      },
      "ios": {
        "buildConfiguration": "Release"
      },
      "env": {
        "EXPO_PUBLIC_API_URL": "https://splendid-bravery-production.up.railway.app"
      }
    }
  },
  "submit": {
    "production": {}
  }
}
